{
	"authors": [
		"Jan Allersma"
	],
	"copyright": "Copyright © 2022, Jan Allersma",
	"dependencies": {
		"arsd-official:dom": "~>11.2.2"
	},
	"description": "A minimal D application.",
	"dflags": [
		"-L-lstdc++"
	],
	"lflags": [
		"-Lbuild",
		"-lsdlwrapper",
		"-lSDL2",
		"-lSDL2_ttf",
		"-lSDL2_image",
		"-L/usr/local/homebrew/Cellar/sdl2/2.28.4/lib/",
		"-L/usr/local/homebrew/Cellar/sdl2_ttf/2.20.2/lib/"
	],
	"license": "proprietary",
	"name": "printplaat",
	"preBuildCommands": [
		"./build-wrapper"
	],
	"sourcePaths": [
		"src"
	],
	"targetType": "executable",
	"targetPath": "build"
}
